[
  {
    "title": "Pulp Fiction",
    "year": 1964,
    "rating": 6.1
  },
  {
    "title": "The Shawshank Redemption",
    "year": 1985,
    "rating": 6.9
  },
  {
    "title": "The Godfather",
    "year": 1967,
    "rating": 8.6
  },
  {
    "title": "The Dark Knight",
    "year": 2019,
    "rating": 6.3
  },
  {
    "title": "12 Angry Men",
    "year": 2004,
    "rating": 6.1
  },
  {
    "title": "Schindler's List",
    "year": 1961,
    "rating": 6.8
  },
  {
    "title": "The Lord of the Rings: The Return of the King",
    "year": 2014,
    "rating": 8.1
  },
  {
    "title": "Forrest Gump",
    "year": 2021,
    "rating": 6.7
  },
  {
    "title": "Inception",
    "year": 2019,
    "rating": 7.5
  },
  {
    "title": "Fight Club",
    "year": 2007,
    "rating": 8.1
  },
  {
    "title": "Pulp Fiction",
    "year": 1950,
    "rating": 8.7
  },
  {
    "title": "The Shawshank Redemption",
    "year": 1970,
    "rating": 8.4
  },
  {
    "title": "The Godfather",
    "year": 1993,
    "rating": 7.0
  },
  {
    "title": "The Dark Knight",
    "year": 1977,
    "rating": 9.4
  },
  {
    "title": "12 Angry Men",
    "year": 1993,
    "rating": 6.4
  },
  {
    "title": "Schindler's List",
    "year": 1998,
    "rating": 6.3
  },
  {
    "title": "The Lord of the Rings: The Return of the King",
    "year": 1994,
    "rating": 8.1
  },
  {
    "title": "Forrest Gump",
    "year": 1955,
    "rating": 8.6
  },
  {
    "title": "Inception",
    "year": 2018,
    "rating": 6.4
  },
  {
    "title": "Fight Club",
    "year": 1998,
    "rating": 6.3
  },
  {
    "title": "Pulp Fiction",
    "year": 1987,
    "rating": 8.9
  },
  {
    "title": "The Shawshank Redemption",
    "year": 1996,
    "rating": 8.0
  },
  {
    "title": "The Godfather",
    "year": 1958,
    "rating": 6.2
  },
  {
    "title": "The Dark Knight",
    "year": 1979,
    "rating": 8.7
  },
  {
    "title": "12 Angry Men",
    "year": 1960,
    "rating": 9.0
  },
  {
    "title": "Schindler's List",
    "year": 1962,
    "rating": 7.3
  },
  {
    "title": "The Lord of the Rings: The Return of the King",
    "year": 2008,
    "rating": 8.2
  },
  {
    "title": "Forrest Gump",
    "year": 1996,
    "rating": 6.6
  },
  {
    "title": "Inception",
    "year": 1995,
    "rating": 6.7
  },
  {
    "title": "Fight Club",
    "year": 1984,
    "rating": 8.5
  },
  {
    "title": "Pulp Fiction",
    "year": 1959,
    "rating": 8.1
  },
  {
    "title": "The Shawshank Redemption",
    "year": 1971,
    "rating": 7.9
  },
  {
    "title": "The Godfather",
    "year": 1981,
    "rating": 6.6
  },
  {
    "title": "The Dark Knight",
    "year": 1998,
    "rating": 6.9
  },
  {
    "title": "12 Angry Men",
    "year": 2021,
    "rating": 6.8
  },
  {
    "title": "Schindler's List",
    "year": 1991,
    "rating": 8.9
  },
  {
    "title": "The Lord of the Rings: The Return of the King",
    "year": 1957,
    "rating": 6.8
  },
  {
    "title": "Forrest Gump",
    "year": 1954,
    "rating": 8.8
  },
  {
    "title": "Inception",
    "year": 2001,
    "rating": 6.9
  },
  {
    "title": "Fight Club",
    "year": 1977,
    "rating": 9.2
  },
  {
    "title": "Pulp Fiction",
    "year": 2022,
    "rating": 9.1
  },
  {
    "title": "The Shawshank Redemption",
    "year": 1990,
    "rating": 6.7
  },
  {
    "title": "The Godfather",
    "year": 2013,
    "rating": 7.4
  },
  {
    "title": "The Dark Knight",
    "year": 2008,
    "rating": 6.5
  },
  {
    "title": "12 Angry Men",
    "year": 1967,
    "rating": 6.9
  },
  {
    "title": "Schindler's List",
    "year": 2021,
    "rating": 7.9
  },
  {
    "title": "The Lord of the Rings: The Return of the King",
    "year": 2004,
    "rating": 9.1
  },
  {
    "title": "Forrest Gump",
    "year": 2001,
    "rating": 7.3
  },
  {
    "title": "Inception",
    "year": 1967,
    "rating": 7.8
  },
  {
    "title": "Fight Club",
    "year": 1961,
    "rating": 8.6
  },
  {
    "title": "Pulp Fiction",
    "year": 1964,
    "rating": 6.5
  },
  {
    "title": "The Shawshank Redemption",
    "year": 1970,
    "rating": 8.8
  },
  {
    "title": "The Godfather",
    "year": 2004,
    "rating": 8.1
  },
  {
    "title": "The Dark Knight",
    "year": 1999,
    "rating": 7.3
  },
  {
    "title": "12 Angry Men",
    "year": 2009,
    "rating": 7.9
  },
  {
    "title": "Schindler's List",
    "year": 2020,
    "rating": 9.0
  },
  {
    "title": "The Lord of the Rings: The Return of the King",
    "year": 1951,
    "rating": 8.4
  },
  {
    "title": "Forrest Gump",
    "year": 1964,
    "rating": 8.4
  },
  {
    "title": "Inception",
    "year": 2018,
    "rating": 8.6
  },
  {
    "title": "Fight Club",
    "year": 1993,
    "rating": 6.4
  },
  {
    "title": "Pulp Fiction",
    "year": 2005,
    "rating": 6.6
  },
  {
    "title": "The Shawshank Redemption",
    "year": 1950,
    "rating": 9.3
  },
  {
    "title": "The Godfather",
    "year": 1983,
    "rating": 9.4
  },
  {
    "title": "The Dark Knight",
    "year": 1972,
    "rating": 7.8
  },
  {
    "title": "12 Angry Men",
    "year": 1963,
    "rating": 9.0
  },
  {
    "title": "Schindler's List",
    "year": 1988,
    "rating": 8.9
  },
  {
    "title": "The Lord of the Rings: The Return of the King",
    "year": 2014,
    "rating": 8.1
  },
  {
    "title": "Forrest Gump",
    "year": 1969,
    "rating": 7.3
  },
  {
    "title": "Inception",
    "year": 1970,
    "rating": 7.9
  },
  {
    "title": "Fight Club",
    "year": 2017,
    "rating": 9.2
  },
  {
    "title": "Pulp Fiction",
    "year": 1991,
    "rating": 7.7
  },
  {
    "title": "The Shawshank Redemption",
    "year": 1964,
    "rating": 9.3
  },
  {
    "title": "The Godfather",
    "year": 1989,
    "rating": 6.8
  },
  {
    "title": "The Dark Knight",
    "year": 1980,
    "rating": 9.1
  },
  {
    "title": "12 Angry Men",
    "year": 1960,
    "rating": 6.3
  },
  {
    "title": "Schindler's List",
    "year": 2012,
    "rating": 8.9
  },
  {
    "title": "The Lord of the Rings: The Return of the King",
    "year": 2018,
    "rating": 8.7
  },
  {
    "title": "Forrest Gump",
    "year": 1966,
    "rating": 8.3
  },
  {
    "title": "Inception",
    "year": 2020,
    "rating": 6.6
  },
  {
    "title": "Fight Club",
    "year": 2017,
    "rating": 9.1
  },
  {
    "title": "Pulp Fiction",
    "year": 2004,
    "rating": 9.4
  },
  {
    "title": "The Shawshank Redemption",
    "year": 2019,
    "rating": 8.6
  },
  {
    "title": "The Godfather",
    "year": 1975,
    "rating": 8.5
  },
  {
    "title": "The Dark Knight",
    "year": 2001,
    "rating": 9.5
  },
  {
    "title": "12 Angry Men",
    "year": 1997,
    "rating": 7.5
  },
  {
    "title": "Schindler's List",
    "year": 2016,
    "rating": 7.6
  },
  {
    "title": "The Lord of the Rings: The Return of the King",
    "year": 1981,
    "rating": 6.8
  },
  {
    "title": "Forrest Gump",
    "year": 1993,
    "rating": 6.1
  },
  {
    "title": "Inception",
    "year": 2020,
    "rating": 6.8
  },
  {
    "title": "Fight Club",
    "year": 1978,
    "rating": 6.0
  },
  {
    "title": "Pulp Fiction",
    "year": 1957,
    "rating": 6.8
  },
  {
    "title": "The Shawshank Redemption",
    "year": 1954,
    "rating": 9.0
  },
  {
    "title": "The Godfather",
    "year": 1959,
    "rating": 7.8
  },
  {
    "title": "The Dark Knight",
    "year": 1985,
    "rating": 8.3
  },
  {
    "title": "12 Angry Men",
    "year": 1977,
    "rating": 7.9
  },
  {
    "title": "Schindler's List",
    "year": 2023,
    "rating": 8.0
  },
  {
    "title": "The Lord of the Rings: The Return of the King",
    "year": 1981,
    "rating": 8.7
  },
  {
    "title": "Forrest Gump",
    "year": 2002,
    "rating": 6.7
  },
  {
    "title": "Inception",
    "year": 1962,
    "rating": 8.3
  },
  {
    "title": "Fight Club",
    "year": 1995,
    "rating": 7.5
  }
]